{
	"configurations" : 
	[
		{
			"directories" : 
			[
				{
					"build" : ".",
					"hasInstallRule" : true,
					"jsonFile" : "directory-.-Debug-b5507cb53e3f690e4c7b.json",
					"minimumCMakeVersion" : 
					{
						"string" : "3.5"
					},
					"projectIndex" : 0,
					"source" : ".",
					"targetIndexes" : 
					[
						0
					]
				}
			],
			"name" : "Debug",
			"projects" : 
			[
				{
					"directoryIndexes" : 
					[
						0
					],
					"name" : "math_winkel",
					"targetIndexes" : 
					[
						0
					]
				}
			],
			"targets" : 
			[
				{
					"directoryIndex" : 0,
					"id" : "math_winkel::@6890427a1f51a3e7e1df",
					"jsonFile" : "target-math_winkel-Debug-cfff1b9d742459bb8835.json",
					"name" : "math_winkel",
					"projectIndex" : 0
				}
			]
		}
	],
	"kind" : "codemodel",
	"paths" : 
	{
		"build" : "/home/roman/qt code/build-math_winkel-Desktop_Qt_6_6_1_GCC_64bit-Debug",
		"source" : "/home/roman/qt code/math_winkel"
	},
	"version" : 
	{
		"major" : 2,
		"minor" : 6
	}
}
