{
	"configurations" : 
	[
		{
			"directories" : 
			[
				{
					"build" : ".",
					"hasInstallRule" : true,
					"jsonFile" : "directory-.-Debug-fedcc6597413cbbf0712.json",
					"minimumCMakeVersion" : 
					{
						"string" : "3.5"
					},
					"projectIndex" : 0,
					"source" : ".",
					"targetIndexes" : 
					[
						0
					]
				}
			],
			"name" : "Debug",
			"projects" : 
			[
				{
					"directoryIndexes" : 
					[
						0
					],
					"name" : "13_35_bitset_funktion",
					"targetIndexes" : 
					[
						0
					]
				}
			],
			"targets" : 
			[
				{
					"directoryIndex" : 0,
					"id" : "13_35_bitset_funktion::@6890427a1f51a3e7e1df",
					"jsonFile" : "target-13_35_bitset_funktion-Debug-b1801cb6844892d03fb8.json",
					"name" : "13_35_bitset_funktion",
					"projectIndex" : 0
				}
			]
		}
	],
	"kind" : "codemodel",
	"paths" : 
	{
		"build" : "C:/Qt/Projects/Qt/build-13_35_bitset_funktion-Desktop_Qt_6_5_0_MinGW_64_bit-Debug",
		"source" : "C:/Qt/Projects/Qt/13_35_bitset_funktion"
	},
	"version" : 
	{
		"major" : 2,
		"minor" : 4
	}
}
