{
	"configurations" : 
	[
		{
			"directories" : 
			[
				{
					"build" : ".",
					"hasInstallRule" : true,
					"jsonFile" : "directory-.-Debug-74f0972459841a9ef94c.json",
					"minimumCMakeVersion" : 
					{
						"string" : "3.5"
					},
					"projectIndex" : 0,
					"source" : ".",
					"targetIndexes" : 
					[
						0
					]
				}
			],
			"name" : "Debug",
			"projects" : 
			[
				{
					"directoryIndexes" : 
					[
						0
					],
					"name" : "13_20_container_stack",
					"targetIndexes" : 
					[
						0
					]
				}
			],
			"targets" : 
			[
				{
					"directoryIndex" : 0,
					"id" : "13_20_container_stack::@6890427a1f51a3e7e1df",
					"jsonFile" : "target-13_20_container_stack-Debug-cf6b7305d217a147ecb9.json",
					"name" : "13_20_container_stack",
					"projectIndex" : 0
				}
			]
		}
	],
	"kind" : "codemodel",
	"paths" : 
	{
		"build" : "C:/Qt/Projects/Qt/build-13_20_container_stack-Desktop_Qt_6_5_0_MinGW_64_bit-Debug",
		"source" : "C:/Qt/Projects/Qt/13_20_container_stack"
	},
	"version" : 
	{
		"major" : 2,
		"minor" : 4
	}
}
